Workbook

Sheet Read Me
B2: Meesho Limited - Financial Model & Valuation Workbook
B3: Companion to the IPO research report · all figures ₹ crore unless stated
B6: CONTENTS
B7: • Financials - reconciled income statement & cost structure, FY23–H1 FY26
B8: • Ratios - growth, margin, efficiency, per-unit and valuation ratios (live formulas)
B9: • DCF - 10-year discounted-cash-flow valuation with editable assumptions
B10: • Sensitivity - fair value per share across WACC × terminal-growth (live 2-way grid)
B11: • Comps - listed peer comparison (market data)
B13: HOW TO USE
B14: Change the blue assumption cells on the DCF sheet (revenue growth, FCF margin, WACC,
B15: terminal growth, net cash). The DCF, per-share value and the Sensitivity grid update
B16: automatically. The Ratios sheet recomputes from the Financials sheet.
... B23: Independent academic exercise for educational purposes. Not investment advice. Figures are drawn from public filings and cited secondary sources and may contain estimation error; verify against the RHP before any decision. Valuation is illustrative.

Sheet Financials
A1: Reconciled Financial Summary (₹ crore)
A2: Source: Meesho RHP/DRHP (SEBI); reconciled across filings. Blank = not separately disclosed.
A4: Particulars | B4: FY23 | C4: FY24 | D4: FY25 | E4: H1 FY26
A5: Revenue from operations | B5: 5734.5 | C5: 7615.1 | D5: 9389.9 | E5: 5577.5
A6: Total income (incl. other) | B6: - | C6: - | D6: 9900.9 | E6: -
A7: Logistics & fulfilment | B7: 4817 | C7: 5926.8 | D7: 7352 | E7: 4429
A8: Advertising & sales promotion | B8: 928 | C8: 459.4 | D8: 643.5 | E8: 606
A9: Employee benefits | B9: - | C9: 757.7 | D9: 848.1 | E9: -
A10: Server & software / cloud | B10: 567 | C10: - | D10: 620 | E10: 437
A11: Total expenditure | B11: - | C11: 8173.7 | D11: 10009.3 | E11: -
A12: Reported net profit / (loss) | B12: -1671.9 | C12: -327.6 | D12: -3941.7 | E12: -700.7
A13: Exceptional: business-combination tax | B13: - | C13: - | D13: 2487.3 | E13: -
A14: Exceptional: reorg & accelerated ESOP | B14: - | C14: - | D14: 1346 | E14: -
A15: Operating profit / (loss) ex-exceptionals | B15: - | C15: - | D15: -108.4 | E15: -433
A16: Free cash flow | B16: -2336 | C16: 304 | D16: 351 | E16: -
A17: Net merchandise value (NMV) | B17: - | C17: - | D17: - | E17: 19194
A19: OPERATING METRICS
A20: Annual transacting users (crore) | B20: 13.64 | C20: - | D20: 19.88 | E20: 23.42
A21: Annual transacting sellers ('000) | B21: - | C21: - | D21: - | E21: 706.5
A22: Placed orders (crore) | B22: - | C22: - | D22: 183 | E22: 126.1
A23: Order frequency (x) | B23: 7.5 | C23: - | D23: - | E23: 9.7
A24: Average order value (₹) | B24: - | C24: - | D24: - | E24: 265.5
A25: Contribution margin (% of NMV) | B25: 0.0294 | C25: - | D25: 0.0495 | E25: 0.0382
A26: Cash-on-delivery (% orders) | B26: 0.8871 | C26: 0.8539 | D26: 0.7695 | E26: 0.72
A27: Take rate (%) | B27: - | C27: - | D27: 0.305 | E27: -
A28: Full-time employees | B28: - | C28: - | D28: - | E28: 2082

Sheet Ratios
A1: Financial Ratio Analysis
A2: Computed live from the Financials sheet. Green = cross-sheet link.
A4: Ratio | B4: FY23 | C4: FY24 | D4: FY25 | E4: H1 FY26
A5: Revenue growth (YoY) | B5: - | C5: =Financials!C5/Financials!B5-1 -> 0.32794489 | D5: =Financials!D5/Financials!C5-1 -> 0.23306326 | E5: =Financials!E5/4311.3-1 -> 0.29369332
A6: Revenue CAGR FY23–FY25 | B6: - | C6: - | D6: =(Financials!D5/Financials!B5)^(1/2)-1 -> 0.27962497 | E6: -
A7: Contribution margin (% NMV) | B7: =Financials!B25 -> 0.0294 | C7: - | D7: =Financials!D25 -> 0.0495 | E7: =Financials!E25 -> 0.0382
A8: Net margin - reported | B8: =Financials!B12/Financials!B5 -> -0.29155114 | C8: =Financials!C12/Financials!C5 -> -0.04301979 | D8: =Financials!D12/Financials!D5 -> -0.41978083 | E8: =Financials!E12/Financials!E5 -> -0.12562976
A9: Net margin - ex-exceptionals | B9: - | C9: - | D9: =Financials!D15/Financials!D5 -> -0.011544319 | E9: =Financials!E15/Financials!E5 -> -0.077633348
A10: Logistics cost / revenue | B10: =Financials!B7/Financials!B5 -> 0.84000349 | C10: =Financials!C7/Financials!C5 -> 0.77829575 | D10: =Financials!D7/Financials!D5 -> 0.78296893 | E10: =Financials!E7/Financials!E5 -> 0.79408337
A11: Advertising / revenue | B11: =Financials!B8/Financials!B5 -> 0.16182754 | C11: =Financials!C8/Financials!C5 -> 0.060327507 | D11: =Financials!D8/Financials!D5 -> 0.068531081 | E11: =Financials!E8/Financials!E5 -> 0.10865083
A12: Employee cost / revenue | B12: - | C12: =Financials!C9/Financials!C5 -> 0.099499678 | D12: =Financials!D9/Financials!D5 -> 0.090320451 | E12: -
A13: FCF margin | B13: =Financials!B16/Financials!B5 -> -0.40735897 | C13: =Financials!C16/Financials!C5 -> 0.039920684 | D13: =Financials!D16/Financials!D5 -> 0.03738059 | E13: -
A14: Revenue per employee (₹ cr) | B14: - | C14: - | D14: =Financials!D5/Financials!E28 -> 4.5100384 | E14: -
A15: Contribution per order (₹) | B15: - | C15: - | D15: 8.09 | E15: -
A17: VALUATION (at issue price ₹111)
A18: Market capitalisation (₹ cr) | B18: 50096
A19: Price / Sales (FY25 revenue) | B19: =B18/Financials!D5 -> 5.3350941
A20: Market cap / annual user (₹) | B20: =B18/Financials!D20 -> 2519.9195
A21: Net debt / equity | B21: 0
A23: Note: Return ratios (ROE/ROCE) are not meaningful for FY25 - losses and the one-time
A24: reverse-flip capital restructuring distort the denominator; discussed in report commentary.

Sheet DCF
A1: Discounted Cash Flow Valuation (illustrative)
A2: Editable assumptions in blue/yellow. FCFF is independent of WACC & g, which drives the live Sensitivity grid.
A4: Base revenue FY25 (₹ cr) | B4: 9389.9
A5: WACC | B5: 0.13
A6: Terminal growth (g) | B6: 0.05
A7: Net cash (₹ cr) | B7: 2500
A8: Shares outstanding (crore) | B8: 451.31
A11: Projection year | C11: FY26E | D11: FY27E | E11: FY28E | F11: FY29E | G11: FY30E | H11: FY31E | I11: FY32E | J11: FY33E | K11: FY34E | L11: FY35E
A12: Period (t) | C12: 1 | D12: 2 | E12: 3 | F12: 4 | G12: 5 | H12: 6 | I12: 7 | J12: 8 | K12: 9 | L12: 10
A13: Revenue growth | C13: 0.3 | D13: 0.28 | E13: 0.25 | F13: 0.22 | G13: 0.2 | H13: 0.18 | I13: 0.16 | J13: 0.14 | K13: 0.12 | L13: 0.1
A14: Revenue (₹ cr) | C14: =$B$4*(1+C13) -> 12206.87 | D14: =C14*(1+D13) -> 15624.794 | E14: =D14*(1+E13) -> 19530.992 | F14: =E14*(1+F13) -> 23827.81 | G14: =F14*(1+G13) -> 28593.372 | H14: =G14*(1+H13) -> 33740.179 | I14: =H14*(1+I13) -> 39138.608 | J14: =I14*(1+J13) -> 44618.013 | K14: =J14*(1+K13) -> 49972.175 | L14: =K14*(1+L13) -> 54969.392
A15: FCF margin | C15: 0.02 | D15: 0.04 | E15: 0.06 | F15: 0.08 | G15: 0.1 | H15: 0.12 | I15: 0.14 | J15: 0.16 | K15: 0.18 | L15: 0.2
A16: FCFF (₹ cr) | C16: =C14*C15 -> 244.1374 | D16: =D14*D15 -> 624.99174 | E16: =E14*E15 -> 1171.8595 | F16: =F14*F15 -> 1906.2248 | G16: =G14*G15 -> 2859.3372 | H16: =H14*H15 -> 4048.8215 | I16: =I14*I15 -> 5479.4051 | J16: =J14*J15 -> 7138.8821 | ... L16: =L14*L15 -> 10993.878
A17: Discount factor | C17: =1/(1+$B$5)^C12 -> 0.88495575 | D17: =1/(1+$B$5)^D12 -> 0.78314668 | E17: =1/(1+$B$5)^E12 -> 0.69305016 | F17: =1/(1+$B$5)^F12 -> 0.61331873 | G17: =1/(1+$B$5)^G12 -> 0.54275994 | H17: =1/(1+$B$5)^H12 -> 0.48031853 | I17: =1/(1+$B$5)^I12 -> 0.42506064 | J17: =1/(1+$B$5)^J12 -> 0.37615986 | ... L17: =1/(1+$B$5)^L12 -> 0.29458835
A18: PV of FCFF (₹ cr) | C18: =C16*C17 -> 216.0508 | D18: =D16*D17 -> 489.46021 | E18: =E16*E17 -> 812.15743 | F18: =F16*F17 -> 1169.1234 | G18: =G16*G17 -> 1551.9337 | H18: =H16*H17 -> 1944.724 | I18: =I16*I17 -> 2329.0795 | J18: =J16*J17 -> 2685.3609 | ... L18: =L16*L17 -> 3238.6685
A20: Sum of PV of explicit FCFF | C20: =SUM(C18:L18) -> 17430.855
A21: Terminal value (FY35E) | C21: =L16*(1+$B$6)/($B$5-$B$6) -> 144294.65
A22: PV of terminal value | C22: =C21/(1+$B$5)^L12 -> 42507.524
A23: Enterprise value | C23: =C20+C22 -> 59938.378
A24: (+) Net cash | C24: =$B$7 -> 2500
A25: Equity value | C25: =C23+C24 -> 62438.378
A26: Fair value per share (₹) | C26: =C25/$B$8 -> 138.3492
A28: Reference points: issue price ₹111 · current market ₹192 (30-Jun-26) · Choice Equity DCF ₹160–185

Sheet Sensitivity
A1: DCF Sensitivity - fair value per share (₹)
A2: Live grid: each cell re-runs the DCF at that WACC × terminal-growth. Base case boxed in report.
A4: WACC \ g | B4: 0.03 | C4: 0.04 | D4: 0.05 | E4: 0.055 | F4: 0.06
A5: 0.12 | B5: =(SUMPRODUCT(DCF!$C$16:$L$16,1/(1+$A5)^DCF!$C$12:$L$12)+(DCF!$L$16*(1+B$4)/($A5-B$4))/(1+$A5)^10+DCF!$B$7)/DCF!$B$8 -> 136.47179 | C5: =(SUMPRODUCT(DCF!$C$16:$L$16,1/(1+$A5)^DCF!$C$12:$L$12)+(DCF!$L$16*(1+C$4)/($A5-C$4))/(1+$A5)^10+DCF!$B$7)/DCF!$B$8 -> 148.67239 | D5: =(SUMPRODUCT(DCF!$C$16:$L$16,1/(1+$A5)^DCF!$C$12:$L$12)+(DCF!$L$16*(1+D$4)/($A5-D$4))/(1+$A5)^10+DCF!$B$7)/DCF!$B$8 -> 164.35888 | E5: =(SUMPRODUCT(DCF!$C$16:$L$16,1/(1+$A5)^DCF!$C$12:$L$12)+(DCF!$L$16*(1+E$4)/($A5-E$4))/(1+$A5)^10+DCF!$B$7)/DCF!$B$8 -> 174.01211 | F5: =(SUMPRODUCT(DCF!$C$16:$L$16,1/(1+$A5)^DCF!$C$12:$L$12)+(DCF!$L$16*(1+F$4)/($A5-F$4))/(1+$A5)^10+DCF!$B$7)/DCF!$B$8 -> 185.2742
A6: 0.13 | B6: =(SUMPRODUCT(DCF!$C$16:$L$16,1/(1+$A6)^DCF!$C$12:$L$12)+(DCF!$L$16*(1+B$4)/($A6-B$4))/(1+$A6)^10+DCF!$B$7)/DCF!$B$8 -> 118.07658 | C6: =(SUMPRODUCT(DCF!$C$16:$L$16,1/(1+$A6)^DCF!$C$12:$L$12)+(DCF!$L$16*(1+C$4)/($A6-C$4))/(1+$A6)^10+DCF!$B$7)/DCF!$B$8 -> 127.08663 | D6: =(SUMPRODUCT(DCF!$C$16:$L$16,1/(1+$A6)^DCF!$C$12:$L$12)+(DCF!$L$16*(1+D$4)/($A6-D$4))/(1+$A6)^10+DCF!$B$7)/DCF!$B$8 -> 138.3492 | E6: =(SUMPRODUCT(DCF!$C$16:$L$16,1/(1+$A6)^DCF!$C$12:$L$12)+(DCF!$L$16*(1+E$4)/($A6-E$4))/(1+$A6)^10+DCF!$B$7)/DCF!$B$8 -> 145.10674 | F6: =(SUMPRODUCT(DCF!$C$16:$L$16,1/(1+$A6)^DCF!$C$12:$L$12)+(DCF!$L$16*(1+F$4)/($A6-F$4))/(1+$A6)^10+DCF!$B$7)/DCF!$B$8 -> 152.82965
A7: 0.14 | B7: =(SUMPRODUCT(DCF!$C$16:$L$16,1/(1+$A7)^DCF!$C$12:$L$12)+(DCF!$L$16*(1+B$4)/($A7-B$4))/(1+$A7)^10+DCF!$B$7)/DCF!$B$8 -> 103.33563 | C7: =(SUMPRODUCT(DCF!$C$16:$L$16,1/(1+$A7)^DCF!$C$12:$L$12)+(DCF!$L$16*(1+C$4)/($A7-C$4))/(1+$A7)^10+DCF!$B$7)/DCF!$B$8 -> 110.14551 | D7: =(SUMPRODUCT(DCF!$C$16:$L$16,1/(1+$A7)^DCF!$C$12:$L$12)+(DCF!$L$16*(1+D$4)/($A7-D$4))/(1+$A7)^10+DCF!$B$7)/DCF!$B$8 -> 118.4687 | E7: =(SUMPRODUCT(DCF!$C$16:$L$16,1/(1+$A7)^DCF!$C$12:$L$12)+(DCF!$L$16*(1+E$4)/($A7-E$4))/(1+$A7)^10+DCF!$B$7)/DCF!$B$8 -> 123.36469 | F7: =(SUMPRODUCT(DCF!$C$16:$L$16,1/(1+$A7)^DCF!$C$12:$L$12)+(DCF!$L$16*(1+F$4)/($A7-F$4))/(1+$A7)^10+DCF!$B$7)/DCF!$B$8 -> 128.87269
A8: 0.15 | B8: =(SUMPRODUCT(DCF!$C$16:$L$16,1/(1+$A8)^DCF!$C$12:$L$12)+(DCF!$L$16*(1+B$4)/($A8-B$4))/(1+$A8)^10+DCF!$B$7)/DCF!$B$8 -> 91.313612 | C8: =(SUMPRODUCT(DCF!$C$16:$L$16,1/(1+$A8)^DCF!$C$12:$L$12)+(DCF!$L$16*(1+C$4)/($A8-C$4))/(1+$A8)^10+DCF!$B$7)/DCF!$B$8 -> 96.55953 | D8: =(SUMPRODUCT(DCF!$C$16:$L$16,1/(1+$A8)^DCF!$C$12:$L$12)+(DCF!$L$16*(1+D$4)/($A8-D$4))/(1+$A8)^10+DCF!$B$7)/DCF!$B$8 -> 102.85463 | E8: =(SUMPRODUCT(DCF!$C$16:$L$16,1/(1+$A8)^DCF!$C$12:$L$12)+(DCF!$L$16*(1+E$4)/($A8-E$4))/(1+$A8)^10+DCF!$B$7)/DCF!$B$8 -> 106.49916 | F8: =(SUMPRODUCT(DCF!$C$16:$L$16,1/(1+$A8)^DCF!$C$12:$L$12)+(DCF!$L$16*(1+F$4)/($A8-F$4))/(1+$A8)^10+DCF!$B$7)/DCF!$B$8 -> 110.54864
A9: 0.16 | B9: =(SUMPRODUCT(DCF!$C$16:$L$16,1/(1+$A9)^DCF!$C$12:$L$12)+(DCF!$L$16*(1+B$4)/($A9-B$4))/(1+$A9)^10+DCF!$B$7)/DCF!$B$8 -> 81.364743 | C9: =(SUMPRODUCT(DCF!$C$16:$L$16,1/(1+$A9)^DCF!$C$12:$L$12)+(DCF!$L$16*(1+C$4)/($A9-C$4))/(1+$A9)^10+DCF!$B$7)/DCF!$B$8 -> 85.470842 | D9: =(SUMPRODUCT(DCF!$C$16:$L$16,1/(1+$A9)^DCF!$C$12:$L$12)+(DCF!$L$16*(1+D$4)/($A9-D$4))/(1+$A9)^10+DCF!$B$7)/DCF!$B$8 -> 90.323505 | E9: =(SUMPRODUCT(DCF!$C$16:$L$16,1/(1+$A9)^DCF!$C$12:$L$12)+(DCF!$L$16*(1+E$4)/($A9-E$4))/(1+$A9)^10+DCF!$B$7)/DCF!$B$8 -> 93.096456 | F9: =(SUMPRODUCT(DCF!$C$16:$L$16,1/(1+$A9)^DCF!$C$12:$L$12)+(DCF!$L$16*(1+F$4)/($A9-F$4))/(1+$A9)^10+DCF!$B$7)/DCF!$B$8 -> 96.146701
A11: Base case: WACC 13%, g 5% (highlighted). Green→ cheaper vs price; red→ demanding.

Sheet Comps
A1: Listed Peer Comparison
A2: Market data indicative, ~June 2026; revenue years differ by company (labelled). For context, not strict like-for-like.
A4: Company | B4: Model | C4: Revenue (₹cr) | D4: Rev yr | E4: Net profit | F4: Profitable? | G4: Mkt cap (₹cr) | H4: P/S (x)
A5: Meesho | B5: Value marketplace | C5: 9389.9 | D5: FY25 | E5: (108) adj | F5: Near-BE | G5: 50096 | H5: =G5/C5 -> 5.3350941
A6: Eternal (Zomato) | B6: Food + q-comm | C6: 20000 | D6: FY26E | E6: Profit | F6: Yes | G6: 240000 | H6: =G6/C6 -> 12
A7: Swiggy | B7: Food + q-comm | C7: 15227 | D7: FY25 | E7: Loss | F7: No | G7: 58000 | H7: =G7/C7 -> 3.8090234
A8: Nykaa (FSN) | B8: Beauty/fashion | C8: 10022 | D8: FY26 | E8: 204 | F8: Yes | G8: 88500 | H8: =G8/C8 -> 8.8305727
A9: FirstCry (Brainbees) | B9: Kids & baby | C9: 7660 | D9: FY25 | E9: Thin | F9: Marginal | G9: 11772 | H9: =G9/C9 -> 1.5368146
A10: Avenue Supermarts (DMart) | B10: Value retail | C10: 59000 | D10: FY25 | E10: Profit | F10: Yes | G10: 270000 | H10: =G10/C10 -> 4.5762712
A12: Sources: Screener.in, exchange data, company filings (~Jun-2026). Swiggy/Eternal revenue are estimates.
